chastack_bdd/__init__.py
chastack_bdd/__main__.py
chastack_bdd/bdd.py
chastack_bdd/registro.py
chastack_bdd/tabla.py
chastack_bdd/utiles.py
chastack_bdd/errores/__init__.py
chastack_bdd/tipos/__init__.py
chastack_bdd/tipos/enum_sql.py
chastack_bdd/tipos/unico_sql.py
chastack_bdd/usuario/__init__.py
chastack_bdd/usuario/errores.py
chastack_bdd/usuario/usuario.py
chastack_bdd-0.8.1.dist-info/licenses/LICENSE
chastack_bdd-0.8.1.dist-info/METADATA
chastack_bdd-0.8.1.dist-info/WHEEL
chastack_bdd-0.8.1.dist-info/top_level.txt
chastack_bdd-0.8.1.dist-info/RECORD
