Metadata-Version: 2.4
Name: chastack-bdd
Version: 0.8.1
Summary: Abstracción de Bases de Datos en Python y constructor de modelos.
Home-page: https://github.com/Hernanatn/bdd.py
Author: Hernán A. Teszkiewicz Novick
Author-email: "Hernán A.T.N." <herni@cajadeideas.ar>, Joaquín Correa <correajoaquin7@gmail.com>, "Camila M.T.N." <cmteszkiewicz@gmail.com>
Project-URL: Homepage, https://github.com/Hernanatn/bdd.py
Classifier: Programming Language :: Python :: 3
Classifier: License :: OSI Approved :: MIT License
Classifier: Operating System :: OS Independent
Requires-Python: >=3.13
License-File: LICENSE
Requires-Dist: sobrecargar
Requires-Dist: solteron
Requires-Dist: mysql-connector-python<9.2.1,>=8.2.0
Dynamic: author
Dynamic: home-page
Dynamic: license-file
